MANIFEST.in
README.txt
setup.py
docs/HISTORY.txt
src/infrae/__init__.py
src/infrae.layout.egg-info/PKG-INFO
src/infrae.layout.egg-info/SOURCES.txt
src/infrae.layout.egg-info/dependency_links.txt
src/infrae.layout.egg-info/namespace_packages.txt
src/infrae.layout.egg-info/not-zip-safe
src/infrae.layout.egg-info/requires.txt
src/infrae.layout.egg-info/top_level.txt
src/infrae/layout/__init__.py
src/infrae/layout/components.py
src/infrae/layout/configure.zcml
src/infrae/layout/interfaces.py
src/infrae/layout/meta.py
src/infrae/layout/tests/__init__.py