Metadata-Version: 1.0
Name: infrae.layout
Version: 1.0
Summary: Layout system for Zope 2
Home-page: http://svn.infrae.com/infrae.layout/trunk
Author: Sylvain Viollon
Author-email: info@infrae.com
License: ZPL
Keywords: zope2 layout silva infrae
Platform: UNKNOWN
Classifier: Environment :: Web Environment
Classifier: Intended Audience :: Developers
Classifier: License :: OSI Approved :: Zope Public License
Classifier: Programming Language :: Python
Classifier: Topic :: Software Development :: Libraries :: Python Modules
Classifier: Framework :: Zope2
